LICENSE.txt
MANIFEST.in
README.rst
setup.cfg
setup.py
DeepLearningStack/__init__.py
DeepLearningStack.egg-info/PKG-INFO
DeepLearningStack.egg-info/SOURCES.txt
DeepLearningStack.egg-info/dependency_links.txt
DeepLearningStack.egg-info/entry_points.txt
DeepLearningStack.egg-info/requires.txt
DeepLearningStack.egg-info/top_level.txt
DeepLearningStack/Config/__init__.py
DeepLearningStack/ConvNet/BatchNormalize.py
DeepLearningStack/ConvNet/Conv.py
DeepLearningStack/ConvNet/Deconv.py
DeepLearningStack/ConvNet/Deflatten.py
DeepLearningStack/ConvNet/DepthConcat.py
DeepLearningStack/ConvNet/LRN.py
DeepLearningStack/ConvNet/Normalize.py
DeepLearningStack/ConvNet/Pool.py
DeepLearningStack/ConvNet/__init__.py
DeepLearningStack/Core/Concatenate.py
DeepLearningStack/Core/Dropout.py
DeepLearningStack/Core/ElementWise.py
DeepLearningStack/Core/FeedForwardNet.py
DeepLearningStack/Core/Flatten.py
DeepLearningStack/Core/LU.py
DeepLearningStack/Core/Rectifier.py
DeepLearningStack/Core/Sigmoid.py
DeepLearningStack/Core/Softmax.py
DeepLearningStack/Core/Tanh.py
DeepLearningStack/Core/__init__.py
DeepLearningStack/Input/Data.py
DeepLearningStack/Input/Img.py
DeepLearningStack/Input/__init__.py
DeepLearningStack/Mem/GRU.py
DeepLearningStack/Mem/LSTM.py
DeepLearningStack/Mem/__init__.py
DeepLearningStack/RL/ActionSelection.py
DeepLearningStack/RL/DirichletLayer.py
DeepLearningStack/RL/Gaussian.py
DeepLearningStack/RL/GaussianObs.py
DeepLearningStack/RL/NaiveBayesBeliefUpdate.py
DeepLearningStack/RL/__init__.py
DeepLearningStack/RNN/RecurrentNet.py
DeepLearningStack/RNN/__init__.py