Metadata-Version: 1.0
Name: DeepLearningStack
Version: 0.0.9
Summary: A Python package for creating deep network graphs using Theano
Home-page: https://github.com/mohsenmalmir/DeepLearningStack
Author: Mohsen Malmir
Author-email: mmalmir@ucsd.edu
License: MIT
Download-URL: https://github.com/mohsenmalmir/DeepLearningStack/tarball/0.0.9
Keywords: deep recurrent neural network reinforcement learning
Platform: UNKNOWN
Classifier: Development Status :: 3 - Alpha
Classifier: Intended Audience :: Developers
Classifier: Topic :: Software Development :: Build Tools
Classifier: License :: OSI Approved :: MIT License
Classifier: Programming Language :: Python :: 2
Classifier: Programming Language :: Python :: 2.6
Classifier: Programming Language :: Python :: 2.7
